AUTHORS.txt
CHANGES.txt
README.rst
README.txt
development.ini
setup.cfg
setup.py
kotti_blog/__init__.py
kotti_blog/batch.py
kotti_blog/fanstatic.py
kotti_blog/populate.py
kotti_blog/resources.py
kotti_blog/views.py
kotti_blog.egg-info/PKG-INFO
kotti_blog.egg-info/SOURCES.txt
kotti_blog.egg-info/dependency_links.txt
kotti_blog.egg-info/entry_points.txt
kotti_blog.egg-info/not-zip-safe
kotti_blog.egg-info/requires.txt
kotti_blog.egg-info/top_level.txt
kotti_blog/locale/kotti_blog.pot
kotti_blog/locale/de/LC_MESSAGES/kotti_blog.po
kotti_blog/locale/en/LC_MESSAGES/kotti_blog.po
kotti_blog/static/kotti_blog.js
kotti_blog/static/kotti_blog.min.js
kotti_blog/static/loader.gif
kotti_blog/static/style.css
kotti_blog/static/style.min.css
kotti_blog/templates/blog-view.pt
kotti_blog/templates/blogentry-view.pt
kotti_blog/templates/macros.pt
kotti_blog/tests/__init__.py
kotti_blog/tests/conftest.py
kotti_blog/tests/test_batching.txt
kotti_blog/tests/test_blog.py
kotti_blog/tests/test_browser.txt
local/AUTHORS.txt
local/CHANGES.txt
local/README.rst
local/README.txt
local/development.ini
local/setup.cfg
local/setup.py
local/kotti_blog/__init__.py
local/kotti_blog/batch.py
local/kotti_blog/fanstatic.py
local/kotti_blog/populate.py
local/kotti_blog/resources.py
local/kotti_blog/views.py
local/kotti_blog/locale/kotti_blog.pot
local/kotti_blog/locale/de/LC_MESSAGES/kotti_blog.po
local/kotti_blog/locale/en/LC_MESSAGES/kotti_blog.po
local/kotti_blog/static/kotti_blog.js
local/kotti_blog/static/kotti_blog.min.js
local/kotti_blog/static/loader.gif
local/kotti_blog/static/style.css
local/kotti_blog/static/style.min.css
local/kotti_blog/templates/blog-view.pt
local/kotti_blog/templates/blogentry-view.pt
local/kotti_blog/templates/macros.pt
local/kotti_blog/tests/__init__.py
local/kotti_blog/tests/conftest.py
local/kotti_blog/tests/test_batching.txt
local/kotti_blog/tests/test_blog.py
local/kotti_blog/tests/test_browser.txt