Metadata-Version: 1.1
Name: kotti-blog
Version: 0.4
Summary: Add a simple blog to your Kotti site
Home-page: http://pypi.python.org/pypi/kotti_blog
Author: Marco Scheidhuber
Author-email: j23d@jusid.de
License: BSD-derived (http://www.repoze.org/LICENSE.txt)
Keywords: kotti blog
Platform: UNKNOWN
Classifier: Programming Language :: Python
Classifier: Programming Language :: Python :: 2.6
Classifier: Programming Language :: Python :: 2.7
Classifier: Framework :: Pylons
Classifier: Topic :: Internet :: WWW/HTTP
Classifier: Topic :: Internet :: WWW/HTTP :: Dynamic Content
Classifier: Topic :: Internet :: WWW/HTTP :: WSGI :: Application
Classifier: License :: Repoze Public License
